PassCrypt/__init__.py
PassCrypt/main.py
PassCrypt-1.0.0.dist-info/METADATA
PassCrypt-1.0.0.dist-info/WHEEL
PassCrypt-1.0.0.dist-info/top_level.txt
PassCrypt-1.0.0.dist-info/RECORD
