Metadata-Version: 2.1
Name: PassCrypt
Version: 1.0.0
